LICENSE.txt
README.md
hayes2009.py
setup.py
hayes2009.egg-info/PKG-INFO
hayes2009.egg-info/SOURCES.txt
hayes2009.egg-info/dependency_links.txt
hayes2009.egg-info/not-zip-safe
hayes2009.egg-info/top_level.txt