Metadata-Version: 2.1
Name: hayes2009
Version: 0.1
Summary: Phonological feature charts from Hayes 2009
Home-page: https://github.com/kylebgorman/hayes2009
Author: Kyle Gorman
Author-email: kylebgorman@gmail.com
License: Apache 2.0
Keywords: computational linguistics,natural language processing,phonology,phonetics,speech,language
Platform: UNKNOWN
Classifier: Programming Language :: Python :: 3.7
Classifier: Programming Language :: Python :: 3.8
Classifier: Programming Language :: Python :: 3.9
Classifier: Programming Language :: Python :: 3.10
Classifier: Development Status :: 4 - Beta
Classifier: Environment :: Console
Classifier: License :: OSI Approved :: Apache Software License
Classifier: Operating System :: OS Independent
Classifier: Topic :: Text Processing :: Linguistic
Requires-Python: >=3.7
License-File: LICENSE.txt
